[{"line":1,"elements":[{"start_timestamp":"2022-06-29T21:12:27.246Z","before":[{"result":{"duration":1000000,"status":"passed"},"match":{"location":"StepsForHooks.HooksDemoSteps.browserSetup2()"}},{"result":{"duration":2611000000,"status":"passed"},"match":{"location":"StepsForHooks.HooksDemoSteps.browserSetup()"}}],"line":4,"name":"","description":"","id":"check-login-functionality-with-hooks;","after":[{"result":{"status":"passed"},"match":{"location":"StepsForHooks.HooksDemoSteps.tearDown2()"}},{"result":{"duration":678000000,"status":"passed"},"match":{"location":"StepsForHooks.HooksDemoSteps.tearDown()"}}],"type":"scenario","keyword":"Scenario","steps":[{"result":{"status":"passed"},"before":[{"result":{"status":"passed"},"match":{"location":"StepsForHooks.HooksDemoSteps.beforeSteps()"}}],"line":5,"name":"User is on login page","match":{"location":"StepsForHooks.HooksDemoSteps.user_is_on_login_page()"},"after":[{"result":{"status":"passed"},"match":{"location":"StepsForHooks.HooksDemoSteps.afterSteps()"}}],"keyword":"Given "},{"result":{"status":"passed"},"before":[{"result":{"status":"passed"},"match":{"location":"StepsForHooks.HooksDemoSteps.beforeSteps()"}}],"line":6,"name":"User enters valid username and password","match":{"location":"StepsForHooks.HooksDemoSteps.User_enters_valid_username_and_password()"},"after":[{"result":{"status":"passed"},"match":{"location":"StepsForHooks.HooksDemoSteps.afterSteps()"}}],"keyword":"When "},{"result":{"status":"passed"},"before":[{"result":{"status":"passed"},"match":{"location":"StepsForHooks.HooksDemoSteps.beforeSteps()"}}],"line":7,"name":"Clicks on login button","match":{"location":"StepsForHooks.HooksDemoSteps.clicks_on_login_button()"},"after":[{"result":{"status":"passed"},"match":{"location":"StepsForHooks.HooksDemoSteps.afterSteps()"}}],"keyword":"And "},{"result":{"status":"passed"},"before":[{"result":{"status":"passed"},"match":{"location":"StepsForHooks.HooksDemoSteps.beforeSteps()"}}],"line":8,"name":"User is navigated to the home page","match":{"location":"StepsForHooks.HooksDemoSteps.user_is_navigated_to_the_home_page()"},"after":[{"result":{"status":"passed"},"match":{"location":"StepsForHooks.HooksDemoSteps.afterSteps()"}}],"keyword":"Then "}],"tags":[{"name":"@Smoke"}]},{"start_timestamp":"2022-06-29T21:12:30.595Z","before":[{"result":{"status":"passed"},"match":{"location":"StepsForHooks.HooksDemoSteps.browserSetup2()"}},{"result":{"duration":1268000000,"status":"passed"},"match":{"location":"StepsForHooks.HooksDemoSteps.browserSetup()"}}],"line":10,"name":"","description":"","id":"check-login-functionality-with-hooks;","after":[{"result":{"status":"passed"},"match":{"location":"StepsForHooks.HooksDemoSteps.tearDown2()"}},{"result":{"duration":654000000,"status":"passed"},"match":{"location":"StepsForHooks.HooksDemoSteps.tearDown()"}}],"type":"scenario","keyword":"Scenario","steps":[{"result":{"status":"passed"},"before":[{"result":{"status":"passed"},"match":{"location":"StepsForHooks.HooksDemoSteps.beforeSteps()"}}],"line":11,"name":"User is on login page","match":{"location":"StepsForHooks.HooksDemoSteps.user_is_on_login_page()"},"after":[{"result":{"status":"passed"},"match":{"location":"StepsForHooks.HooksDemoSteps.afterSteps()"}}],"keyword":"Given "},{"result":{"status":"passed"},"before":[{"result":{"status":"passed"},"match":{"location":"StepsForHooks.HooksDemoSteps.beforeSteps()"}}],"line":12,"name":"User enters valid username and password","match":{"location":"StepsForHooks.HooksDemoSteps.User_enters_valid_username_and_password()"},"after":[{"result":{"status":"passed"},"match":{"location":"StepsForHooks.HooksDemoSteps.afterSteps()"}}],"keyword":"When "},{"result":{"status":"passed"},"before":[{"result":{"status":"passed"},"match":{"location":"StepsForHooks.HooksDemoSteps.beforeSteps()"}}],"line":13,"name":"Clicks on login button","match":{"location":"StepsForHooks.HooksDemoSteps.clicks_on_login_button()"},"after":[{"result":{"status":"passed"},"match":{"location":"StepsForHooks.HooksDemoSteps.afterSteps()"}}],"keyword":"And "},{"result":{"status":"passed"},"before":[{"result":{"status":"passed"},"match":{"location":"StepsForHooks.HooksDemoSteps.beforeSteps()"}}],"line":14,"name":"User is navigated to the home page","match":{"location":"StepsForHooks.HooksDemoSteps.user_is_navigated_to_the_home_page()"},"after":[{"result":{"status":"passed"},"match":{"location":"StepsForHooks.HooksDemoSteps.afterSteps()"}}],"keyword":"Then "}]}],"name":"Check login functionality with hooks","description":"","id":"check-login-functionality-with-hooks","keyword":"Feature","uri":"file:src/test/resources/HooksDemo/HooksDemo.feature","tags":[]}]